rubaliz/__init__.py
rubaliz/__version__.py
rubaliz/rubaliz.py
rubaliz/seabird/__init__.py
rubaliz/seabird/cnv.py
rubaliz/seabird/exceptions.py
rubaliz/seabird/utils.py
rubaliz/seabird/rules/cnv.json
rubaliz/seabird/rules/cnv.yaml
rubaliz/seabird/rules/cnv2.json
rubaliz/seabird/rules/cnv3.json
rubaliz/seabird/rules/cnv4.json
rubaliz/seabird/rules/cnv_binary.json
rubaliz/seabird/rules/cnv_btl.json
rubaliz/seabird/rules/refnames.json
rubaliz-0.1.11.dist-info/LICENSE
rubaliz-0.1.11.dist-info/METADATA
rubaliz-0.1.11.dist-info/WHEEL
rubaliz-0.1.11.dist-info/top_level.txt
rubaliz-0.1.11.dist-info/RECORD
