Metadata-Version: 2.1
Name: rubaliz
Version: 0.1.11
Summary: A package to detect the boundaries of the active mesopelagic zone
Home-page: https://github.com/RobeeF/rubaliz/
Author: Robin Fuchs
Author-email: robin.fuchs92@gmail.com
License: UNKNOWN
Platform: UNKNOWN
Classifier: Programming Language :: Python :: 3.7
Classifier: License :: OSI Approved :: GNU General Public License v3 (GPLv3)
License-File: LICENSE
Requires-Dist: numpy (>=1.17.1)
Requires-Dist: pandas (>=1.0.3)
Requires-Dist: ruptures (>=1.1.5)
Requires-Dist: matplotlib (>=3.4.0)
